{"thrid":"8d3d0dfd-2fae-4f29-84d7-ab97375c050d","title":"てすと","contents":[{"name":"名無し","text":"⛭","id":"TV-aI6D","timestamp":"2025/01/28 20:53:12"},{"name":"名無し","text":"!aa\n　　 　　　＿＿＿_\n  　　　／　　 　 　＼\n  　 ／　　─　 　 ─＼\n  ／ 　　 （●） 　（●） ＼\n  |　 　　 　 （__人__）　 　 |\n  ./　　　　 ∩ノ ⊃　　／\n  (　 ＼　／ ＿ノ　|　 |\n  .＼　“　　／＿＿|　 |\n  　　＼ ／＿＿＿ ／ ","id":"TV-paa9","timestamp":"2025/02/01 20:59:02"},{"name":"名無し","text":"!IFR:&quot;https://openosv.net/main/&quot;","id":"TV-cGWN","timestamp":"2025/02/01 21:02:28"},{"name":"名無しさん","text":"なんやここ","id":"V:LEz6","timestamp":"2025/02/02 23:38:55"},{"name":"名無し","text":"!URL:&quot;javascript:(function(){var main_ = document.createElement(&quot;div&quot;);main_.style = `position: fixed;top:0vw;left:0vw;padding:4px; background-color: #efefef; color: black`;main_.innerHTML=&quot;こんにちは&quot;;document.querySelectorAll(&quot;body&quot;)[0].appendChild(main_);})()&quot;","id":"V-xSyr","timestamp":"2025/02/03 04:43:07"}]}